ecg_sample_setup/__init__.py
ecg_sample_setup-0.1.5.dist-info/LICENSE
ecg_sample_setup-0.1.5.dist-info/WHEEL
ecg_sample_setup-0.1.5.dist-info/METADATA
ecg_sample_setup-0.1.5.dist-info/RECORD
