Metadata-Version: 2.1
Name: ecg-sample-setup
Version: 0.1.5
Summary: 
Author: RobC
Author-email: rob.clapham@gmail.com
Requires-Python: >=3.9,<4.0
Classifier: Programming Language :: Python :: 3
Classifier: Programming Language :: Python :: 3.10
Classifier: Programming Language :: Python :: 3.9
Requires-Dist: poetry (>=1.1.14,<2.0.0)
